dash_utility_components/RadioImages.py
dash_utility_components/__init__.py
dash_utility_components/_imports_.py
dash_utility_components/dash_utility_components.min.js
dash_utility_components/dash_utility_components.min.js.map
dash_utility_components/metadata.json
dash_utility_components/package-info.json
dash_utility_components-0.0.1.dist-info/LICENSE
dash_utility_components-0.0.1.dist-info/METADATA
dash_utility_components-0.0.1.dist-info/WHEEL
dash_utility_components-0.0.1.dist-info/top_level.txt
dash_utility_components-0.0.1.dist-info/RECORD
