Metadata-Version: 2.1
Name: dash-utility-components
Version: 0.0.1
Summary: Components that do a little more than others.
Home-page: UNKNOWN
Author: Brad Erickson <brad@trainerhill.com>
Author-email: UNKNOWN
License: MIT
Platform: UNKNOWN
Classifier: Framework :: Dash
